{
  "content": [
    {
      "content": null,
      "created": "2022-11-29T00:12:39.565490Z",
      "format": null,
      "last_modified": "2022-11-29T00:12:18.685129Z",
      "mimetype": null,
      "name": "data-science-python-plotting.ipynb",
      "path": "data-science-python-plotting.ipynb",
      "size": 141355,
      "type": "notebook",
      "writable": true
    },
    {
      "content": null,
      "created": "2022-11-29T00:12:39.561490Z",
      "format": null,
      "last_modified": "2022-11-29T00:12:18.685129Z",
      "mimetype": null,
      "name": "data-science-python-basics.ipynb",
      "path": "data-science-python-basics.ipynb",
      "size": 159954,
      "type": "notebook",
      "writable": true
    },
    {
      "content": null,
      "created": "2022-11-29T00:12:39.561490Z",
      "format": null,
      "last_modified": "2022-11-29T00:12:18.681129Z",
      "mimetype": null,
      "name": "data-science-python-advanced-np-pd.ipynb",
      "path": "data-science-python-advanced-np-pd.ipynb",
      "size": 114827,
      "type": "notebook",
      "writable": true
    }
  ],
  "created": "2022-11-29T00:12:39.565490Z",
  "format": "json",
  "last_modified": "2022-11-29T00:12:39.565490Z",
  "mimetype": null,
  "name": "",
  "path": "",
  "size": null,
  "type": "directory",
  "writable": true
}