{
  "content": "{\n    \"a_galaxy_workflow\": \"true\",\n    \"annotation\": \"\",\n    \"creator\": [{\"class\": \"Person\", \"identifier\":\"0000-0001-6585-3619\", \"name\": \"Kaivan Kamali\"}],\n    \"format-version\": \"0.1\",\n    \"license\": \"CC-BY-4.0\",\n    \"name\": \"Intro_To_RNN_v1_0_10_0\",\n    \"steps\": {\n        \"0\": {\n            \"annotation\": \"\",\n            \"content_id\": null,\n            \"errors\": null,\n            \"id\": 0,\n            \"input_connections\": {},\n            \"inputs\": [\n                {\n                    \"description\": \"\",\n                    \"name\": \"X_test\"\n                }\n            ],\n            \"label\": \"X_test\",\n            \"name\": \"Input dataset\",\n            \"outputs\": [],\n            \"position\": {\n                \"left\": 10,\n                \"top\": 10\n            },\n            \"tool_id\": null,\n            \"tool_state\": \"{\\\"optional\\\": false, \\\"tag\\\": null}\",\n            \"tool_version\": null,\n            \"type\": \"data_input\",\n            \"uuid\": \"c84eb1e9-61dc-4d37-b13e-999665b31337\",\n            \"when\": null,\n            \"workflow_outputs\": []\n        },\n        \"1\": {\n            \"annotation\": \"\",\n            \"content_id\": null,\n            \"errors\": null,\n            \"id\": 1,\n            \"input_connections\": {},\n            \"inputs\": [\n                {\n                    \"description\": \"\",\n                    \"name\": \"X_train\"\n                }\n            ],\n            \"label\": \"X_train\",\n            \"name\": \"Input dataset\",\n            \"outputs\": [],\n            \"position\": {\n                \"left\": 10,\n                \"top\": 130\n            },\n            \"tool_id\": null,\n            \"tool_state\": \"{\\\"optional\\\": false, \\\"tag\\\": null}\",\n            \"tool_version\": null,\n            \"type\": \"data_input\",\n            \"uuid\": \"0e7e1ec8-f422-4349-889a-4e3e66670c2f\",\n            \"when\": null,\n            \"workflow_outputs\": []\n        },\n        \"2\": {\n            \"annotation\": \"\",\n            \"content_id\": null,\n            \"errors\": null,\n            \"id\": 2,\n            \"input_connections\": {},\n            \"inputs\": [\n                {\n                    \"description\": \"\",\n                    \"name\": \"y_test\"\n                }\n            ],\n            \"label\": \"y_test\",\n            \"name\": \"Input dataset\",\n            \"outputs\": [],\n            \"position\": {\n                \"left\": 10,\n                \"top\": 250\n            },\n            \"tool_id\": null,\n            \"tool_state\": \"{\\\"optional\\\": false, \\\"tag\\\": null}\",\n            \"tool_version\": null,\n            \"type\": \"data_input\",\n            \"uuid\": \"ec09b380-de33-44e1-bce4-c203c10c47d6\",\n            \"when\": null,\n            \"workflow_outputs\": []\n        },\n        \"3\": {\n            \"annotation\": \"\",\n            \"content_id\": null,\n            \"errors\": null,\n            \"id\": 3,\n            \"input_connections\": {},\n            \"inputs\": [\n                {\n                    \"description\": \"\",\n                    \"name\": \"y_train\"\n                }\n            ],\n            \"label\": \"y_train\",\n            \"name\": \"Input dataset\",\n            \"outputs\": [],\n            \"position\": {\n                \"left\": 10,\n                \"top\": 370\n            },\n            \"tool_id\": null,\n            \"tool_state\": \"{\\\"optional\\\": false, \\\"tag\\\": null}\",\n            \"tool_version\": null,\n            \"type\": \"data_input\",\n            \"uuid\": \"e0784c26-64c5-4135-ad67-03c62a362b7b\",\n            \"when\": null,\n            \"workflow_outputs\": []\n        },\n        \"4\": {\n            \"annotation\": \"\",\n            \"content_id\": \"toolshed.g2.bx.psu.edu/repos/bgruening/keras_model_config/keras_model_config/1.0.10.0\",\n            \"errors\": null,\n            \"id\": 4,\n            \"input_connections\": {},\n            \"inputs\": [],\n            \"label\": null,\n            \"name\": \"Create a deep learning model architecture\",\n            \"outputs\": [\n                {\n                    \"name\": \"outfile\",\n                    \"type\": \"json\"\n                }\n            ],\n            \"position\": {\n                \"left\": 10,\n                \"top\": 490\n            },\n            \"post_job_actions\": {},\n            \"tool_id\": \"toolshed.g2.bx.psu.edu/repos/bgruening/keras_model_config/keras_model_config/1.0.10.0\",\n            \"tool_shed_repository\": {\n                \"changeset_revision\": \"f22a9297440f\",\n                \"name\": \"keras_model_config\",\n                \"owner\": \"bgruening\",\n                \"tool_shed\": \"toolshed.g2.bx.psu.edu\"\n            },\n            \"tool_state\": \"{\\\"__input_ext\\\": \\\"input\\\", \\\"chromInfo\\\": \\\"/cvmfs/data.galaxyproject.org/managed/len/ucsc/?.len\\\", \\\"model_selection\\\": {\\\"model_type\\\": \\\"sequential\\\", \\\"__current_case__\\\": 0, \\\"input_shape\\\": \\\"(500, )\\\", \\\"layers\\\": [{\\\"__index__\\\": 0, \\\"layer_selection\\\": {\\\"layer_type\\\": \\\"Embedding\\\", \\\"__current_case__\\\": 53, \\\"input_dim\\\": \\\"10000\\\", \\\"output_dim\\\": \\\"32\\\", \\\"kwargs\\\": \\\"\\\"}}, {\\\"__index__\\\": 1, \\\"layer_selection\\\": {\\\"layer_type\\\": \\\"LSTM\\\", \\\"__current_case__\\\": 45, \\\"units\\\": \\\"100\\\", \\\"kwargs\\\": \\\"\\\"}}, {\\\"__index__\\\": 2, \\\"layer_selection\\\": {\\\"layer_type\\\": \\\"Dense\\\", \\\"__current_case__\\\": 0, \\\"units\\\": \\\"1\\\", \\\"activation\\\": \\\"sigmoid\\\", \\\"kwargs\\\": \\\"\\\"}}]}, \\\"__page__\\\": null, \\\"__rerun_remap_job_id__\\\": null}\",\n            \"tool_version\": null,\n            \"type\": \"tool\",\n            \"uuid\": \"f61aba17-35c3-4990-acb9-0e96b0979e7c\",\n            \"when\": null,\n            \"workflow_outputs\": []\n        },\n        \"5\": {\n            \"annotation\": \"\",\n            \"content_id\": \"toolshed.g2.bx.psu.edu/repos/bgruening/ml_visualization_ex/ml_visualization_ex/1.0.8.3\",\n            \"errors\": null,\n            \"id\": 5,\n            \"input_connections\": {\n                \"plotting_selection|infile_true\": {\n                    \"id\": 2,\n                    \"output_name\": \"output\"\n                }\n            },\n            \"inputs\": [],\n            \"label\": null,\n            \"name\": \"Machine Learning Visualization Extension\",\n            \"outputs\": [\n                {\n                    \"name\": \"output\",\n                    \"type\": \"html\"\n                }\n            ],\n            \"position\": {\n                \"left\": 230,\n                \"top\": 10\n            },\n            \"post_job_actions\": {},\n            \"tool_id\": \"toolshed.g2.bx.psu.edu/repos/bgruening/ml_visualization_ex/ml_visualization_ex/1.0.8.3\",\n            \"tool_shed_repository\": {\n                \"changeset_revision\": \"947c2eacccb8\",\n                \"name\": \"ml_visualization_ex\",\n                \"owner\": \"bgruening\",\n                \"tool_shed\": \"toolshed.g2.bx.psu.edu\"\n            },\n            \"tool_state\": \"{\\\"__input_ext\\\": \\\"input\\\", \\\"__workflow_invocation_uuid__\\\": \\\"75b2007ed24c11edba82005056ba2773\\\", \\\"chromInfo\\\": \\\"/cvmfs/data.galaxyproject.org/managed/len/ucsc/?.len\\\", \\\"plotting_selection\\\": {\\\"plot_type\\\": \\\"classification_confusion_matrix\\\", \\\"__current_case__\\\": 6, \\\"infile_true\\\": null, \\\"header_true\\\": false, \\\"column_selector_options_true\\\": {\\\"selected_column_selector_option\\\": \\\"all_columns\\\", \\\"__current_case__\\\": 4}, \\\"infile_predicted\\\": null, \\\"header_predicted\\\": true, \\\"title\\\": \\\"Confusion matrix between true and predicted labels\\\", \\\"plot_format\\\": \\\"png\\\", \\\"plot_color\\\": \\\"Greens\\\"}, \\\"__page__\\\": null, \\\"__rerun_remap_job_id__\\\": null}\",\n            \"tool_version\": null,\n            \"type\": \"tool\",\n            \"uuid\": \"62893cf8-21d5-4f12-b164-bf16d145843d\",\n            \"when\": null,\n            \"workflow_outputs\": []\n        },\n        \"6\": {\n            \"annotation\": \"\",\n            \"content_id\": \"toolshed.g2.bx.psu.edu/repos/bgruening/keras_model_builder/keras_model_builder/1.0.10.0\",\n            \"errors\": null,\n            \"id\": 6,\n            \"input_connections\": {\n                \"mode_selection|infile_json\": {\n                    \"id\": 4,\n                    \"output_name\": \"outfile\"\n                }\n            },\n            \"inputs\": [],\n            \"label\": null,\n            \"name\": \"Create deep learning model\",\n            \"outputs\": [\n                {\n                    \"name\": \"outfile\",\n                    \"type\": \"h5mlm\"\n                }\n            ],\n            \"position\": {\n                \"left\": 230,\n                \"top\": 130\n            },\n            \"post_job_actions\": {},\n            \"tool_id\": \"toolshed.g2.bx.psu.edu/repos/bgruening/keras_model_builder/keras_model_builder/1.0.10.0\",\n            \"tool_shed_repository\": {\n                \"changeset_revision\": \"66d7efc06000\",\n                \"name\": \"keras_model_builder\",\n                \"owner\": \"bgruening\",\n                \"tool_shed\": \"toolshed.g2.bx.psu.edu\"\n            },\n            \"tool_state\": \"{\\\"__input_ext\\\": \\\"input\\\", \\\"chromInfo\\\": \\\"/cvmfs/data.galaxyproject.org/managed/len/ucsc/?.len\\\", \\\"mode_selection\\\": {\\\"mode_type\\\": \\\"train_model\\\", \\\"__current_case__\\\": 0, \\\"infile_json\\\": null, \\\"learning_type\\\": \\\"KerasGClassifier\\\", \\\"compile_params\\\": {\\\"loss\\\": \\\"binary_crossentropy\\\", \\\"optimizer_selection\\\": {\\\"optimizer_type\\\": \\\"Adam\\\", \\\"__current_case__\\\": 4, \\\"optimizer_options\\\": {\\\"learning_rate\\\": \\\"0.001\\\", \\\"beta_1\\\": \\\"0.9\\\", \\\"beta_2\\\": \\\"0.999\\\", \\\"epsilon\\\": \\\"1e-07\\\", \\\"amsgrad\\\": false}}, \\\"metrics\\\": [\\\"acc\\\"]}, \\\"fit_params\\\": {\\\"epochs\\\": \\\"2\\\", \\\"batch_size\\\": \\\"128\\\", \\\"steps_per_epoch\\\": null, \\\"validation_split\\\": \\\"0.1\\\", \\\"validation_steps\\\": null, \\\"callbacks\\\": [{\\\"__index__\\\": 0, \\\"callback_selection\\\": {\\\"callback_type\\\": \\\"None\\\", \\\"__current_case__\\\": 0}}], \\\"verbose\\\": \\\"1\\\"}, \\\"random_seed\\\": null}, \\\"__page__\\\": null, \\\"__rerun_remap_job_id__\\\": null}\",\n            \"tool_version\": null,\n            \"type\": \"tool\",\n            \"uuid\": \"5d389aed-7cba-45bb-b635-526b6b6c12cb\",\n            \"when\": null,\n            \"workflow_outputs\": []\n        },\n        \"7\": {\n            \"annotation\": \"\",\n            \"content_id\": \"toolshed.g2.bx.psu.edu/repos/bgruening/keras_train_and_eval/keras_train_and_eval/1.0.10.0\",\n            \"errors\": null,\n            \"id\": 7,\n            \"input_connections\": {\n                \"experiment_schemes|infile_estimator\": {\n                    \"id\": 6,\n                    \"output_name\": \"outfile\"\n                },\n                \"input_options|infile1\": {\n                    \"id\": 1,\n                    \"output_name\": \"output\"\n                },\n                \"input_options|infile2\": {\n                    \"id\": 3,\n                    \"output_name\": \"output\"\n                }\n            },\n            \"inputs\": [],\n            \"label\": null,\n            \"name\": \"Deep learning training and evaluation\",\n            \"outputs\": [\n                {\n                    \"name\": \"outfile_result\",\n                    \"type\": \"tabular\"\n                },\n                {\n                    \"name\": \"outfile_object\",\n                    \"type\": \"h5mlm\"\n                }\n            ],\n            \"position\": {\n                \"left\": 450,\n                \"top\": 10\n            },\n            \"post_job_actions\": {},\n            \"tool_id\": \"toolshed.g2.bx.psu.edu/repos/bgruening/keras_train_and_eval/keras_train_and_eval/1.0.10.0\",\n            \"tool_shed_repository\": {\n                \"changeset_revision\": \"818f9b69d8a0\",\n                \"name\": \"keras_train_and_eval\",\n                \"owner\": \"bgruening\",\n                \"tool_shed\": \"toolshed.g2.bx.psu.edu\"\n            },\n            \"tool_state\": \"{\\\"__input_ext\\\": \\\"input\\\", \\\"chromInfo\\\": \\\"/cvmfs/data.galaxyproject.org/managed/len/ucsc/?.len\\\", \\\"experiment_schemes\\\": {\\\"selected_exp_scheme\\\": \\\"train_val\\\", \\\"__current_case__\\\": 0, \\\"infile_estimator\\\": null, \\\"hyperparams_swapping\\\": {\\\"param_set\\\": [{\\\"__index__\\\": 0, \\\"sp_name\\\": null, \\\"sp_value\\\": \\\"\\\"}]}, \\\"test_split\\\": {\\\"split_algos\\\": {\\\"shuffle\\\": \\\"simple\\\", \\\"__current_case__\\\": 1, \\\"test_size\\\": \\\"0.2\\\", \\\"random_state\\\": null}}, \\\"metrics\\\": {\\\"scoring\\\": {\\\"primary_scoring\\\": \\\"f1\\\", \\\"__current_case__\\\": 4, \\\"secondary_scoring\\\": null}}}, \\\"input_options\\\": {\\\"selected_input\\\": \\\"tabular\\\", \\\"__current_case__\\\": 0, \\\"infile1\\\": null, \\\"header1\\\": false, \\\"column_selector_options_1\\\": {\\\"selected_column_selector_option\\\": \\\"all_columns\\\", \\\"__current_case__\\\": 4}, \\\"infile2\\\": null, \\\"header2\\\": false, \\\"column_selector_options_2\\\": {\\\"selected_column_selector_option2\\\": \\\"all_columns\\\", \\\"__current_case__\\\": 4}}, \\\"save\\\": [\\\"save_estimator\\\"], \\\"__page__\\\": null, \\\"__rerun_remap_job_id__\\\": null}\",\n            \"tool_version\": null,\n            \"type\": \"tool\",\n            \"uuid\": \"ef36b0d2-4e0e-4247-8763-5b59eb2b859d\",\n            \"when\": null,\n            \"workflow_outputs\": []\n        },\n        \"8\": {\n            \"annotation\": \"\",\n            \"content_id\": \"toolshed.g2.bx.psu.edu/repos/bgruening/model_prediction/model_prediction/1.0.10.0\",\n            \"errors\": null,\n            \"id\": 8,\n            \"input_connections\": {\n                \"infile_estimator\": {\n                    \"id\": 7,\n                    \"output_name\": \"outfile_object\"\n                },\n                \"input_options|infile1\": {\n                    \"id\": 0,\n                    \"output_name\": \"output\"\n                }\n            },\n            \"inputs\": [],\n            \"label\": null,\n            \"name\": \"Model Prediction\",\n            \"outputs\": [\n                {\n                    \"name\": \"outfile_predict\",\n                    \"type\": \"tabular\"\n                }\n            ],\n            \"position\": {\n                \"left\": 670,\n                \"top\": 10\n            },\n            \"post_job_actions\": {},\n            \"tool_id\": \"toolshed.g2.bx.psu.edu/repos/bgruening/model_prediction/model_prediction/1.0.10.0\",\n            \"tool_shed_repository\": {\n                \"changeset_revision\": \"9991c4ddde14\",\n                \"name\": \"model_prediction\",\n                \"owner\": \"bgruening\",\n                \"tool_shed\": \"toolshed.g2.bx.psu.edu\"\n            },\n            \"tool_state\": \"{\\\"__input_ext\\\": \\\"input\\\", \\\"chromInfo\\\": \\\"/cvmfs/data.galaxyproject.org/managed/len/ucsc/?.len\\\", \\\"infile_estimator\\\": null, \\\"input_options\\\": {\\\"selected_input\\\": \\\"tabular\\\", \\\"__current_case__\\\": 0, \\\"infile1\\\": null, \\\"header1\\\": false, \\\"column_selector_options_1\\\": {\\\"selected_column_selector_option\\\": \\\"all_columns\\\", \\\"__current_case__\\\": 4}}, \\\"method\\\": \\\"predict\\\", \\\"__page__\\\": null, \\\"__rerun_remap_job_id__\\\": null}\",\n            \"tool_version\": null,\n            \"type\": \"tool\",\n            \"uuid\": \"84e00c86-0370-4232-b20d-1d54f8c00d6e\",\n            \"when\": null,\n            \"workflow_outputs\": []\n        },\n        \"9\": {\n            \"annotation\": \"\",\n            \"content_id\": \"toolshed.g2.bx.psu.edu/repos/bgruening/ml_visualization_ex/ml_visualization_ex/1.0.10.0\",\n            \"errors\": null,\n            \"id\": 9,\n            \"input_connections\": {\n                \"plotting_selection|infile_predicted\": {\n                    \"id\": 8,\n                    \"output_name\": \"outfile_predict\"\n                },\n                \"plotting_selection|infile_true\": {\n                    \"id\": 2,\n                    \"output_name\": \"output\"\n                }\n            },\n            \"inputs\": [],\n            \"label\": null,\n            \"name\": \"Machine Learning Visualization Extension\",\n            \"outputs\": [\n                {\n                    \"name\": \"output\",\n                    \"type\": \"html\"\n                }\n            ],\n            \"position\": {\n                \"left\": 890,\n                \"top\": 10\n            },\n            \"post_job_actions\": {},\n            \"tool_id\": \"toolshed.g2.bx.psu.edu/repos/bgruening/ml_visualization_ex/ml_visualization_ex/1.0.10.0\",\n            \"tool_shed_repository\": {\n                \"changeset_revision\": \"1588f9076e32\",\n                \"name\": \"ml_visualization_ex\",\n                \"owner\": \"bgruening\",\n                \"tool_shed\": \"toolshed.g2.bx.psu.edu\"\n            },\n            \"tool_state\": \"{\\\"__input_ext\\\": \\\"input\\\", \\\"chromInfo\\\": \\\"/cvmfs/data.galaxyproject.org/managed/len/ucsc/?.len\\\", \\\"plotting_selection\\\": {\\\"plot_type\\\": \\\"classification_confusion_matrix\\\", \\\"__current_case__\\\": 6, \\\"infile_true\\\": null, \\\"header_true\\\": false, \\\"column_selector_options_true\\\": {\\\"selected_column_selector_option\\\": \\\"all_columns\\\", \\\"__current_case__\\\": 4}, \\\"infile_predicted\\\": null, \\\"header_predicted\\\": true, \\\"title\\\": \\\"Confusion matrix between true and predicted labels\\\", \\\"plot_format\\\": \\\"png\\\", \\\"plot_color\\\": \\\"Greens\\\"}, \\\"__page__\\\": null, \\\"__rerun_remap_job_id__\\\": null}\",\n            \"tool_version\": null,\n            \"type\": \"tool\",\n            \"uuid\": \"46cc48a1-b1c9-49fe-9c3c-5996ed4cc592\",\n            \"when\": null,\n            \"workflow_outputs\": []\n        }\n    },\n    \"tags\": [],\n    \"uuid\": \"c995f5c8-de9c-4bc5-9a15-1060eb569d40\",\n    \"version\": 1\n}\n",
  "checksum": [

  ],
  "url": null
}