{
  "layout": "tutorial_hands_on",
  "title": "Introduction to image analysis using Galaxy",
  "zenodo_link": "https://zenodo.org/record/3362976",
  "level": "Introductory",
  "questions": [
    "How do I use Galaxy with imaging data?",
    "How do I convert images using Galaxy?",
    "How do I display images in Galaxy?",
    "How do I filter images in Galaxy?",
    "How do I segment simple images in Galaxy?"
  ],
  "objectives": [
    "How to handle images in Galaxy.",
    "How to perform basic image processing in Galaxy."
  ],
  "key_points": [
    "The **Image Info** tool can provide valuable metadata information of an image.",
    "TIFF files can not directly viewed in the browser, but have to be converted.",
    "For visualization, images with a bit-depth more than 8-bit have to be histogram equalized."
  ],
  "time_estimation": "1H",
  "follow_up_training": [
    {
      "type": "internal",
      "topic_name": "imaging",
      "tutorials": [
        "hela-screen-analysis"
      ]
    }
  ],
  "contributors": [
    {
      "name": "Thomas Wollmann",
      "orcid": "0000-0002-4741-3844",
      "joined": "2019-08",
      "id": "thomaswollmann",
      "url": "https://training.galaxyproject.org/training-material/api/contributors/thomaswollmann.json"
    },
    {
      "name": "Saskia Hiltemann",
      "maintainer_contact": "gitter",
      "email": "saskia.hiltemann@gmail.com",
      "twitter": "shiltemann",
      "linkedin": "shiltemann",
      "gitter": "shiltemann",
      "orcid": "0000-0003-3803-468X",
      "joined": "2017-09",
      "bio": "Researcher at Erasmus Medical Center",
      "id": "shiltemann",
      "url": "https://training.galaxyproject.org/training-material/api/contributors/shiltemann.json"
    }
  ],
  "last_modified_at": "12-Mar-21",
  "url": "/topics/imaging/tutorials/imaging-introduction/tutorial.html",
  "topic_name": "imaging",
  "tutorial_name": "imaging-introduction",
  "hands_on": true,
  "slides": false,
  "workflows": [
    {
      "workflow": "Galaxy-Workflow-GTN_Tutorial__Introduction_to_Imaging.ga",
      "tests": false
    }
  ],
  "tools": [
    "toolshed.g2.bx.psu.edu/repos/imgteam/2d_auto_threshold/ip_threshold/0.0.4",
    "toolshed.g2.bx.psu.edu/repos/imgteam/2d_histogram_equalization/ip_histogram_equalization/0.0.1",
    "toolshed.g2.bx.psu.edu/repos/imgteam/2d_simple_filter/ip_filter_standard/0.0.3",
    "toolshed.g2.bx.psu.edu/repos/imgteam/bfconvert/ip_convertimage/0.4",
    "toolshed.g2.bx.psu.edu/repos/imgteam/binary2labelimage/ip_binary_to_labelimage/0.4",
    "toolshed.g2.bx.psu.edu/repos/imgteam/count_objects/ip_count_objects/0.0.4",
    "toolshed.g2.bx.psu.edu/repos/imgteam/image_info/ip_imageinfo/0.2",
    "toolshed.g2.bx.psu.edu/repos/imgteam/overlay_segmentation_mask/ip_overlay_segmentation/0.0.6",
    "toolshed.g2.bx.psu.edu/repos/imgteam/unzip/unzip/0.2"
  ],
  "tours": false,
  "video": false,
  "translations": {
    "tutorial": [

    ],
    "slides": [

    ],
    "video": false
  },
  "type": "tutorial",
  "urls": {
    "hands_on": "https://training.galaxyproject.org/training-material/api/topics//imaging/tutorials/imaging-introduction/tutorial.json",
    "slides": "https://training.galaxyproject.org/training-material/api/topics//imaging/tutorials/imaging-introduction/tutorial.json"
  }
}