{
  "layout": "tutorial_hands_on",
  "title": "dplyr & tidyverse for data processing",
  "level": "Advanced",
  "enable": false,
  "zenodo_link": null,
  "requirements": [
    {
      "type": "internal",
      "topic_name": "data-science",
      "tutorials": [
        "r-basics",
        "r-advanced"
      ]
    }
  ],
  "follow_up_training": [

  ],
  "questions": [
    "How can I load tabular data into R?",
    "How can I slice and dice the data to ask questions?"
  ],
  "objectives": [
    "Read data with the built-in `read.csv`",
    "Read data with dplyr's `read_csv`",
    "Use dplyr and tidyverse functions to cleanup data."
  ],
  "time_estimation": "1H",
  "key_points": [
    "Dplyr and tidyverse make it a lot easier to process data",
    "The functions for selecting data are a lot easier to understand than R's built in alternatives."
  ],
  "contributors": [
    {
      "name": "Helena Rasche",
      "email": "helena.rasche@gmail.com",
      "orcid": "0000-0001-9760-8992",
      "maintainer_contact": "gitter",
      "gitter": "hexylena",
      "joined": "2017-09",
      "id": "hexylena",
      "url": "https://training.galaxyproject.org/training-material/api/contributors/hexylena.json"
    }
  ],
  "subtopic": "sql",
  "notebook": {
    "language": "r"
  },
  "tags": [
    "R",
    "jupyter-notebook",
    "work-in-progress"
  ],
  "license": "MIT",
  "last_modified_at": "20-Oct-21",
  "url": "/topics/data-science/tutorials/r-dplyr/tutorial.html",
  "topic_name": "data-science",
  "tutorial_name": "r-dplyr"
}